keyring_pybridge/__init__.py
keyring_pybridge/backend.py
keyring_pybridge-0.4.0.dist-info/METADATA
keyring_pybridge-0.4.0.dist-info/WHEEL
keyring_pybridge-0.4.0.dist-info/RECORD
