Metadata-Version: 2.1
Name: keyring-pybridge
Version: 0.4.0
Summary: 
License: MIT
Author: Korijn van Golen
Author-email: korijn.vangolen@zimmerbiomet.com
Requires-Python: >=3.9
Classifier: License :: OSI Approved :: MIT License
Classifier: Programming Language :: Python :: 3
Classifier: Programming Language :: Python :: 3.9
Classifier: Programming Language :: Python :: 3.10
Classifier: Programming Language :: Python :: 3.11
Requires-Dist: keyring (>=24.2.0,<25.0.0)
